{
  "ADDRESS": "5655 PERSHING AV",
  "PROJECTTYPE": "Occupancy",
  "STRUCTURETYPE": 20,
  "STRUCTURETYPENAME": "Commercial",
  "APPLICATIONDATE": "November, 30 2021 00:00:00",
  "ISSUEDATE": "November, 30 2021 00:00:00",
  "DAYSTOISSUE": 0,
  "APPLICATIONDESCRIPTION": "MULTI FAMILY 23 UNITS  (PARTIAL PMT)"
}
{
  "ADDRESS": "3830 JUNIATA ST",
  "PROJECTTYPE": "Occupancy",
  "STRUCTURETYPE": 1,
  "STRUCTURETYPENAME": "1 or 2 Family",
  "APPLICATIONDATE": "November, 30 2021 00:00:00",
  "ISSUEDATE": "November, 30 2021 00:00:00",
  "DAYSTOISSUE": 0,
  "APPLICATIONDESCRIPTION": "SINGLE FAMILY  (PMT)"
}
{
  "ADDRESS": "3700-20 FOREST PARK AV",
  "PROJECTTYPE": "Occupancy",
  "STRUCTURETYPE": 20,
  "STRUCTURETYPENAME": "Commercial",
  "APPLICATIONDATE": "November, 30 2021 00:00:00",
  "ISSUEDATE": "November, 30 2021 00:00:00",
  "DAYSTOISSUE": 0,
  "APPLICATIONDESCRIPTION": "RETAIL SALES - STE 133  (PARTIAL PMT)"
}
{
  "ADDRESS": "3700-20 FOREST PARK AV",
  "PROJECTTYPE": "Occupancy",
  "STRUCTURETYPE": 20,
  "STRUCTURETYPENAME": "Commercial",
  "APPLICATIONDATE": "November, 30 2021 00:00:00",
  "ISSUEDATE": "November, 30 2021 00:00:00",
  "DAYSTOISSUE": 0,
  "APPLICATIONDESCRIPTION": "RETAIL SALES OF NEW FURNITURE - STE 131  (PARTIAL PMT)"
}
{
  "ADDRESS": "3660-2 FAIRVIEW AV",
  "PROJECTTYPE": "Occupancy",
  "STRUCTURETYPE": 20,
  "STRUCTURETYPENAME": "Commercial",
  "APPLICATIONDATE": "November, 30 2021 00:00:00",
  "ISSUEDATE": "November, 30 2021 00:00:00",
  "DAYSTOISSUE": 0,
  "APPLICATIONDESCRIPTION": "HAIR SALON W/ RETAIL SALES OF HAIR PRODUCTS & TOOLS (PMT)"
}
{
  "ADDRESS": "2654-60 LOCUST ST",
  "PROJECTTYPE": "Occupancy",
  "STRUCTURETYPE": 20,
  "STRUCTURETYPENAME": "Commercial",
  "APPLICATIONDATE": "November, 30 2021 00:00:00",
  "ISSUEDATE": "November, 30 2021 00:00:00",
  "DAYSTOISSUE": 0,
  "APPLICATIONDESCRIPTION": "TATTOO STUDIO (NO RETAIL SALES, NO PIERCINGS)  PMT"
}
{
  "ADDRESS": "5852 CLEMENS AV",
  "PROJECTTYPE": "Occupancy",
  "STRUCTURETYPE": 1,
  "STRUCTURETYPENAME": "1 or 2 Family",
  "APPLICATIONDATE": "November, 29 2021 00:00:00",
  "ISSUEDATE": "November, 29 2021 00:00:00",
  "DAYSTOISSUE": 0,
  "APPLICATIONDESCRIPTION": "SINGLE FAMILY  (PMT)"
}
{
  "ADDRESS": "5219 PATTISON AV",
  "PROJECTTYPE": "Occupancy",
  "STRUCTURETYPE": 1,
  "STRUCTURETYPENAME": "1 or 2 Family",
  "APPLICATIONDATE": "November, 23 2021 00:00:00",
  "ISSUEDATE": "November, 23 2021 00:00:00",
  "DAYSTOISSUE": 0,
  "APPLICATIONDESCRIPTION": "SINGLE FAMILY-REAR  (PMT)"
}
{
  "ADDRESS": "3707 MCDONALD AV",
  "PROJECTTYPE": "Occupancy",
  "STRUCTURETYPE": 1,
  "STRUCTURETYPENAME": "1 or 2 Family",
  "APPLICATIONDATE": "November, 23 2021 00:00:00",
  "ISSUEDATE": "November, 23 2021 00:00:00",
  "DAYSTOISSUE": 0,
  "APPLICATIONDESCRIPTION": "SINGLE FAMILY  (PMT)"
}
{
  "ADDRESS": "1711 MARCONI AV",
  "PROJECTTYPE": "Occupancy",
  "STRUCTURETYPE": 1,
  "STRUCTURETYPENAME": "1 or 2 Family",
  "APPLICATIONDATE": "November, 23 2021 00:00:00",
  "ISSUEDATE": "November, 23 2021 00:00:00",
  "DAYSTOISSUE": 0,
  "APPLICATIONDESCRIPTION": "SINGLE FAMILY  (PMT)"
}
{
  "ADDRESS": "1019 PINE ST",
  "PROJECTTYPE": "Occupancy",
  "STRUCTURETYPE": 3,
  "STRUCTURETYPENAME": "Hotel",
  "APPLICATIONDATE": "November, 23 2021 00:00:00",
  "ISSUEDATE": "November, 23 2021 00:00:00",
  "DAYSTOISSUE": 0,
  "APPLICATIONDESCRIPTION": "HOTEL - 96 ROOMS  (BASEMENT THRU 9FL)   PMT"
}
{
  "ADDRESS": "3511 PARK AV",
  "PROJECTTYPE": "Occupancy",
  "STRUCTURETYPE": 1,
  "STRUCTURETYPENAME": "1 or 2 Family",
  "APPLICATIONDATE": "November, 22 2021 00:00:00",
  "ISSUEDATE": "November, 22 2021 00:00:00",
  "DAYSTOISSUE": 0,
  "APPLICATIONDESCRIPTION": "SINGLE FAMILY  (PMT)"
}
{
  "ADDRESS": "1321 S TUCKER BLVD",
  "PROJECTTYPE": "Occupancy",
  "STRUCTURETYPE": 1,
  "STRUCTURETYPENAME": "1 or 2 Family",
  "APPLICATIONDATE": "November, 22 2021 00:00:00",
  "ISSUEDATE": "November, 22 2021 00:00:00",
  "DAYSTOISSUE": 0,
  "APPLICATIONDESCRIPTION": "SINGLE FAMILY  (PMT)"
}
{
  "ADDRESS": "1317 S TUCKER BLVD",
  "PROJECTTYPE": "Occupancy",
  "STRUCTURETYPE": 1,
  "STRUCTURETYPENAME": "1 or 2 Family",
  "APPLICATIONDATE": "November, 22 2021 00:00:00",
  "ISSUEDATE": "November, 22 2021 00:00:00",
  "DAYSTOISSUE": 0,
  "APPLICATIONDESCRIPTION": "SINGLE FAMILY  (PMT)"
}
{
  "ADDRESS": "1212-28 OLIVE ST",
  "PROJECTTYPE": "Occupancy",
  "STRUCTURETYPE": 20,
  "STRUCTURETYPENAME": "Commercial",
  "APPLICATIONDATE": "November, 22 2021 00:00:00",
  "ISSUEDATE": "November, 22 2021 00:00:00",
  "DAYSTOISSUE": 0,
  "APPLICATIONDESCRIPTION": "SITDOWN CARRYOUT RESTAURANT (NO LIQUOR/NO PATIO) PMT"
}
{
  "ADDRESS": "702 N KINGSHIGHWAY BLVD",
  "PROJECTTYPE": "Occupancy",
  "STRUCTURETYPE": 20,
  "STRUCTURETYPENAME": "Commercial",
  "APPLICATIONDATE": "November, 19 2021 00:00:00",
  "ISSUEDATE": "November, 19 2021 00:00:00",
  "DAYSTOISSUE": 0,
  "APPLICATIONDESCRIPTION": "GROCERY STORE WITH 22% BEER/WINE  (NO COOKING)  PMT"
}
{
  "ADDRESS": "511 OLIVE ST",
  "PROJECTTYPE": "Occupancy",
  "STRUCTURETYPE": 20,
  "STRUCTURETYPENAME": "Commercial",
  "APPLICATIONDATE": "November, 19 2021 00:00:00",
  "ISSUEDATE": "November, 19 2021 00:00:00",
  "DAYSTOISSUE": 0,
  "APPLICATIONDESCRIPTION": "MULTI FAMILY 1 UNIT - #706   (PMT)"
}
{
  "ADDRESS": "3245 OREGON AV",
  "PROJECTTYPE": "Occupancy",
  "STRUCTURETYPE": 1,
  "STRUCTURETYPENAME": "1 or 2 Family",
  "APPLICATIONDATE": "November, 18 2021 00:00:00",
  "ISSUEDATE": "November, 19 2021 00:00:00",
  "DAYSTOISSUE": 1,
  "APPLICATIONDESCRIPTION": "SINGLE FAMILY  (PMT)"
}
{
  "ADDRESS": "2342 S 12TH ST",
  "PROJECTTYPE": "Occupancy",
  "STRUCTURETYPE": 1,
  "STRUCTURETYPENAME": "1 or 2 Family",
  "APPLICATIONDATE": "November, 19 2021 00:00:00",
  "ISSUEDATE": "November, 19 2021 00:00:00",
  "DAYSTOISSUE": 0,
  "APPLICATIONDESCRIPTION": "SINGLE FAMILY-PMT"
}
{
  "ADDRESS": "1234 S KINGSHIGHWAY BLVD",
  "PROJECTTYPE": "Occupancy",
  "STRUCTURETYPE": 20,
  "STRUCTURETYPENAME": "Commercial",
  "APPLICATIONDATE": "November, 19 2021 00:00:00",
  "ISSUEDATE": "November, 19 2021 00:00:00",
  "DAYSTOISSUE": 0,
  "APPLICATIONDESCRIPTION": "OFFICE SPACE - STE 1800  (PMT)"
}
{
  "ADDRESS": "6241 LORAN ST",
  "PROJECTTYPE": "Occupancy",
  "STRUCTURETYPE": 1,
  "STRUCTURETYPENAME": "1 or 2 Family",
  "APPLICATIONDATE": "November, 16 2021 00:00:00",
  "ISSUEDATE": "November, 18 2021 00:00:00",
  "DAYSTOISSUE": 2,
  "APPLICATIONDESCRIPTION": "SINGLE FAMILY  (PARTIAL PMT)"
}
{
  "ADDRESS": "5844 MAPLE AV",
  "PROJECTTYPE": "Occupancy",
  "STRUCTURETYPE": 1,
  "STRUCTURETYPENAME": "1 or 2 Family",
  "APPLICATIONDATE": "November, 18 2021 00:00:00",
  "ISSUEDATE": "November, 18 2021 00:00:00",
  "DAYSTOISSUE": 0,
  "APPLICATIONDESCRIPTION": "SINGLE FAMILY-PMT"
}
{
  "ADDRESS": "3700-20 FOREST PARK AV",
  "PROJECTTYPE": "Occupancy",
  "STRUCTURETYPE": 20,
  "STRUCTURETYPENAME": "Commercial",
  "APPLICATIONDATE": "November, 18 2021 00:00:00",
  "ISSUEDATE": "November, 18 2021 00:00:00",
  "DAYSTOISSUE": 0,
  "APPLICATIONDESCRIPTION": "RETAIL SALES OF JEWELRY & MISCELLANEOUS ITEMS  - STE 118"
}
{
  "ADDRESS": "2301 SUBLETTE AV",
  "PROJECTTYPE": "Occupancy",
  "STRUCTURETYPE": 1,
  "STRUCTURETYPENAME": "1 or 2 Family",
  "APPLICATIONDATE": "November, 18 2021 00:00:00",
  "ISSUEDATE": "November, 18 2021 00:00:00",
  "DAYSTOISSUE": 0,
  "APPLICATIONDESCRIPTION": "SINGLE FAMILY  (PMT)"
}
{
  "ADDRESS": "2116 HEREFORD ST",
  "PROJECTTYPE": "Occupancy",
  "STRUCTURETYPE": 1,
  "STRUCTURETYPENAME": "1 or 2 Family",
  "APPLICATIONDATE": "November, 18 2021 00:00:00",
  "ISSUEDATE": "November, 18 2021 00:00:00",
  "DAYSTOISSUE": 0,
  "APPLICATIONDESCRIPTION": "SINGLE FAMILY  (PMT)"
}
{
  "ADDRESS": "2110 BOARDMAN ST",
  "PROJECTTYPE": "Occupancy",
  "STRUCTURETYPE": 1,
  "STRUCTURETYPENAME": "1 or 2 Family",
  "APPLICATIONDATE": "November, 18 2021 00:00:00",
  "ISSUEDATE": "November, 18 2021 00:00:00",
  "DAYSTOISSUE": 0,
  "APPLICATIONDESCRIPTION": "SINGLE FAMILY  (PMT)"
}
{
  "ADDRESS": "2345 PINE ST",
  "PROJECTTYPE": "Occupancy",
  "STRUCTURETYPE": 20,
  "STRUCTURETYPENAME": "Commercial",
  "APPLICATIONDATE": "November, 15 2021 00:00:00",
  "ISSUEDATE": "November, 17 2021 00:00:00",
  "DAYSTOISSUE": 2,
  "APPLICATIONDESCRIPTION": "CONSTRUCTION CO OFFICE SPACE   (PMT)"
}
{
  "ADDRESS": "1352R CENTRAL AV",
  "PROJECTTYPE": "Occupancy",
  "STRUCTURETYPE": 1,
  "STRUCTURETYPENAME": "1 or 2 Family",
  "APPLICATIONDATE": "November, 17 2021 00:00:00",
  "ISSUEDATE": "November, 17 2021 00:00:00",
  "DAYSTOISSUE": 0,
  "APPLICATIONDESCRIPTION": "SINGLE FAMILY  (PMT)"
}
{
  "ADDRESS": "2110 VICTOR ST",
  "PROJECTTYPE": "Occupancy",
  "STRUCTURETYPE": 1,
  "STRUCTURETYPENAME": "1 or 2 Family",
  "APPLICATIONDATE": "November, 16 2021 00:00:00",
  "ISSUEDATE": "November, 16 2021 00:00:00",
  "DAYSTOISSUE": 0,
  "APPLICATIONDESCRIPTION": "TWO FAMILY - 1FL, 2FL  (PMT)"
}
{
  "ADDRESS": "3431 UNION BLVD",
  "PROJECTTYPE": "Occupancy",
  "STRUCTURETYPE": 20,
  "STRUCTURETYPENAME": "Commercial",
  "APPLICATIONDATE": "November, 15 2021 00:00:00",
  "ISSUEDATE": "November, 15 2021 00:00:00",
  "DAYSTOISSUE": 0,
  "APPLICATIONDESCRIPTION": "CLINIC -PMT"
}
{
  "ADDRESS": "3005 LAFAYETTE AV",
  "PROJECTTYPE": "Occupancy",
  "STRUCTURETYPE": 1,
  "STRUCTURETYPENAME": "1 or 2 Family",
  "APPLICATIONDATE": "November, 09 2021 00:00:00",
  "ISSUEDATE": "November, 15 2021 00:00:00",
  "DAYSTOISSUE": 6,
  "APPLICATIONDESCRIPTION": "SINGLE FAMILY  (PMT)"
}
{
  "ADDRESS": "3538 VISTA AV",
  "PROJECTTYPE": "Occupancy",
  "STRUCTURETYPE": 1,
  "STRUCTURETYPENAME": "1 or 2 Family",
  "APPLICATIONDATE": "November, 12 2021 00:00:00",
  "ISSUEDATE": "November, 12 2021 00:00:00",
  "DAYSTOISSUE": 0,
  "APPLICATIONDESCRIPTION": "SINGLE FAMILY- PMT"
}
{
  "ADDRESS": "4669 LOUISIANA AV",
  "PROJECTTYPE": "Occupancy",
  "STRUCTURETYPE": 1,
  "STRUCTURETYPENAME": "1 or 2 Family",
  "APPLICATIONDATE": "November, 10 2021 00:00:00",
  "ISSUEDATE": "November, 10 2021 00:00:00",
  "DAYSTOISSUE": 0,
  "APPLICATIONDESCRIPTION": "SINGLE FAMILY  (PMT)"
}
{
  "ADDRESS": "3700-20 FOREST PARK AV",
  "PROJECTTYPE": "Occupancy",
  "STRUCTURETYPE": 20,
  "STRUCTURETYPENAME": "Commercial",
  "APPLICATIONDATE": "November, 10 2021 00:00:00",
  "ISSUEDATE": "November, 10 2021 00:00:00",
  "DAYSTOISSUE": 0,
  "APPLICATIONDESCRIPTION": "RETAIL SALES - STE 123 & 125 (PARTIAL PMT)"
}
{
  "ADDRESS": "3151 MORGAN FORD RD",
  "PROJECTTYPE": "Occupancy",
  "STRUCTURETYPE": 20,
  "STRUCTURETYPENAME": "Commercial",
  "APPLICATIONDATE": "November, 10 2021 00:00:00",
  "ISSUEDATE": "November, 10 2021 00:00:00",
  "DAYSTOISSUE": 0,
  "APPLICATIONDESCRIPTION": "FULL DRINK BAR & RESTAURANT W/SIDEWALK SEATING  (PMT)"
}
{
  "ADDRESS": "4565-9 MCREE AV",
  "PROJECTTYPE": "Occupancy",
  "STRUCTURETYPE": 20,
  "STRUCTURETYPENAME": "Commercial",
  "APPLICATIONDATE": "November, 08 2021 00:00:00",
  "ISSUEDATE": "November, 09 2021 00:00:00",
  "DAYSTOISSUE": 1,
  "APPLICATIONDESCRIPTION": "FULL DRNK BAR/REST/EVENT SPACE/BEER GARDEN/INDOOR PARK(PMT)"
}
{
  "ADDRESS": "3754 OLIVE ST",
  "PROJECTTYPE": "Occupancy",
  "STRUCTURETYPE": 1,
  "STRUCTURETYPENAME": "1 or 2 Family",
  "APPLICATIONDATE": "November, 09 2021 00:00:00",
  "ISSUEDATE": "November, 09 2021 00:00:00",
  "DAYSTOISSUE": 0,
  "APPLICATIONDESCRIPTION": "SINGLE FAMILY (PMT)"
}
{
  "ADDRESS": "3408 UTAH ST",
  "PROJECTTYPE": "Occupancy",
  "STRUCTURETYPE": 1,
  "STRUCTURETYPENAME": "1 or 2 Family",
  "APPLICATIONDATE": "September, 28 2021 00:00:00",
  "ISSUEDATE": "November, 09 2021 00:00:00",
  "DAYSTOISSUE": 42,
  "APPLICATIONDESCRIPTION": "SINGLE FAMILY  (PMT)"
}
{
  "ADDRESS": "2855 WYOMING ST",
  "PROJECTTYPE": "Occupancy",
  "STRUCTURETYPE": 1,
  "STRUCTURETYPENAME": "1 or 2 Family",
  "APPLICATIONDATE": "September, 23 2021 00:00:00",
  "ISSUEDATE": "November, 09 2021 00:00:00",
  "DAYSTOISSUE": 47,
  "APPLICATIONDESCRIPTION": "SINGLE FAMILY  (PMT)"
}
{
  "ADDRESS": "2631-3 SHENANDOAH AV",
  "PROJECTTYPE": "Occupancy",
  "STRUCTURETYPE": 1,
  "STRUCTURETYPENAME": "1 or 2 Family",
  "APPLICATIONDATE": "November, 09 2021 00:00:00",
  "ISSUEDATE": "November, 09 2021 00:00:00",
  "DAYSTOISSUE": 0,
  "APPLICATIONDESCRIPTION": "FOUR FAMILY-PMT-2631/2631A & 2633/2633A"
}
{
  "ADDRESS": "2122 BOARDMAN ST",
  "PROJECTTYPE": "Occupancy",
  "STRUCTURETYPE": 1,
  "STRUCTURETYPENAME": "1 or 2 Family",
  "APPLICATIONDATE": "November, 09 2021 00:00:00",
  "ISSUEDATE": "November, 09 2021 00:00:00",
  "DAYSTOISSUE": 0,
  "APPLICATIONDESCRIPTION": "SINGLE FAMILY  (PMT)"
}
{
  "ADDRESS": "1630-50 MACKLIND AV",
  "PROJECTTYPE": "Occupancy",
  "STRUCTURETYPE": 20,
  "STRUCTURETYPENAME": "Commercial",
  "APPLICATIONDATE": "November, 09 2021 00:00:00",
  "ISSUEDATE": "November, 09 2021 00:00:00",
  "DAYSTOISSUE": 0,
  "APPLICATIONDESCRIPTION": "MEDICAL MARIJUANA MANUFACTURING (PMT)"
}
{
  "ADDRESS": "1120 N JEFFERSON AV",
  "PROJECTTYPE": "Occupancy",
  "STRUCTURETYPE": 9,
  "STRUCTURETYPENAME": "Hospital",
  "APPLICATIONDATE": "November, 09 2021 00:00:00",
  "ISSUEDATE": "November, 09 2021 00:00:00",
  "DAYSTOISSUE": 0,
  "APPLICATIONDESCRIPTION": "THREE BED TRIAGE HOSPITAL  (PMT)"
}
{
  "ADDRESS": "6000 HALL ST",
  "PROJECTTYPE": "Occupancy",
  "STRUCTURETYPE": 20,
  "STRUCTURETYPENAME": "Commercial",
  "APPLICATIONDATE": "December, 02 2021 00:00:00",
  "ISSUEDATE": "December, 06 2021 00:00:00",
  "DAYSTOISSUE": 4,
  "APPLICATIONDESCRIPTION": "OFFICE SPACE-PMT"
}
{
  "ADDRESS": "5655 PERSHING AV",
  "PROJECTTYPE": "Occupancy",
  "STRUCTURETYPE": 20,
  "STRUCTURETYPENAME": "Commercial",
  "APPLICATIONDATE": "December, 06 2021 00:00:00",
  "ISSUEDATE": "December, 06 2021 00:00:00",
  "DAYSTOISSUE": 0,
  "APPLICATIONDESCRIPTION": "MULTI FAMILY 15 UNITS 418-432 (PARTIAL PMT)"
}
{
  "ADDRESS": "3450 WISCONSIN AV",
  "PROJECTTYPE": "Occupancy",
  "STRUCTURETYPE": 2,
  "STRUCTURETYPENAME": "Multi Family",
  "APPLICATIONDATE": "December, 06 2021 00:00:00",
  "ISSUEDATE": "December, 06 2021 00:00:00",
  "DAYSTOISSUE": 0,
  "APPLICATIONDESCRIPTION": "MULTI FAMILY 42 UNITS (SEE LIST FOR LOADS/UNITS) PARTIAL PMT"
}
{
  "ADDRESS": "6975 SUTHERLAND AV",
  "PROJECTTYPE": "Occupancy",
  "STRUCTURETYPE": 1,
  "STRUCTURETYPENAME": "1 or 2 Family",
  "APPLICATIONDATE": "December, 03 2021 00:00:00",
  "ISSUEDATE": "December, 03 2021 00:00:00",
  "DAYSTOISSUE": 0,
  "APPLICATIONDESCRIPTION": "SINGLE FAMILY  (PMT)"
}
{
  "ADDRESS": "5459 DEMPSEY AV",
  "PROJECTTYPE": "Occupancy",
  "STRUCTURETYPE": 1,
  "STRUCTURETYPENAME": "1 or 2 Family",
  "APPLICATIONDATE": "December, 03 2021 00:00:00",
  "ISSUEDATE": "December, 03 2021 00:00:00",
  "DAYSTOISSUE": 0,
  "APPLICATIONDESCRIPTION": "SINGLE FAMILY  (PMT)"
}
{
  "ADDRESS": "3931 POTOMAC ST",
  "PROJECTTYPE": "Occupancy",
  "STRUCTURETYPE": 1,
  "STRUCTURETYPENAME": "1 or 2 Family",
  "APPLICATIONDATE": "December, 03 2021 00:00:00",
  "ISSUEDATE": "December, 03 2021 00:00:00",
  "DAYSTOISSUE": 0,
  "APPLICATIONDESCRIPTION": "1 UNIT #A  (PMT)"
}
{
  "ADDRESS": "3833-5 N UTAH PL",
  "PROJECTTYPE": "Occupancy",
  "STRUCTURETYPE": 1,
  "STRUCTURETYPENAME": "1 or 2 Family",
  "APPLICATIONDATE": "December, 03 2021 00:00:00",
  "ISSUEDATE": "December, 03 2021 00:00:00",
  "DAYSTOISSUE": 0,
  "APPLICATIONDESCRIPTION": "SINGLE FAMILY  (PMT)"
}
{
  "ADDRESS": "2108 BOARDMAN ST",
  "PROJECTTYPE": "Occupancy",
  "STRUCTURETYPE": 1,
  "STRUCTURETYPENAME": "1 or 2 Family",
  "APPLICATIONDATE": "December, 03 2021 00:00:00",
  "ISSUEDATE": "December, 03 2021 00:00:00",
  "DAYSTOISSUE": 0,
  "APPLICATIONDESCRIPTION": "SINGLE FAMILY  (PMT)"
}
{
  "ADDRESS": "1139 OLIVE ST",
  "PROJECTTYPE": "Occupancy",
  "STRUCTURETYPE": 2,
  "STRUCTURETYPENAME": "Multi Family",
  "APPLICATIONDATE": "December, 03 2021 00:00:00",
  "ISSUEDATE": "December, 03 2021 00:00:00",
  "DAYSTOISSUE": 0,
  "APPLICATIONDESCRIPTION": "MULTIFAM 7 UNITS 403,406,407,408,404,405,409,GYM(PARTIAL PMT"
}
{
  "ADDRESS": "1139 OLIVE ST",
  "PROJECTTYPE": "Occupancy",
  "STRUCTURETYPE": 2,
  "STRUCTURETYPENAME": "Multi Family",
  "APPLICATIONDATE": "December, 03 2021 00:00:00",
  "ISSUEDATE": "December, 03 2021 00:00:00",
  "DAYSTOISSUE": 0,
  "APPLICATIONDESCRIPTION": "MULTI FAMILY 11 UNITS 600-10   (PARTIAL PMT)"
}
{
  "ADDRESS": "3802 CONNECTICUT ST",
  "PROJECTTYPE": "Occupancy",
  "STRUCTURETYPE": 1,
  "STRUCTURETYPENAME": "1 or 2 Family",
  "APPLICATIONDATE": "November, 23 2021 00:00:00",
  "ISSUEDATE": "December, 02 2021 00:00:00",
  "DAYSTOISSUE": 9,
  "APPLICATIONDESCRIPTION": "SINGLE FAMILY  (PMT)"
}
{
  "ADDRESS": "3701-5 S KINGSHIGHWAY BLVD",
  "PROJECTTYPE": "Occupancy",
  "STRUCTURETYPE": 20,
  "STRUCTURETYPENAME": "Commercial",
  "APPLICATIONDATE": "December, 01 2021 00:00:00",
  "ISSUEDATE": "December, 01 2021 00:00:00",
  "DAYSTOISSUE": 0,
  "APPLICATIONDESCRIPTION": "RESTAURANT-1FL(NO LIQUOR, NO COOKING,NO OUTSIDE SEATING) PMT"
}
{
  "ADDRESS": "1139 OLIVE ST",
  "PROJECTTYPE": "Occupancy",
  "STRUCTURETYPE": 20,
  "STRUCTURETYPENAME": "Commercial",
  "APPLICATIONDATE": "November, 30 2021 00:00:00",
  "ISSUEDATE": "December, 01 2021 00:00:00",
  "DAYSTOISSUE": 1,
  "APPLICATIONDESCRIPTION": "OFFICE - UNITS 301-304 (PARTIAL PMT)"
}
{
  "ADDRESS": "1139 OLIVE ST",
  "PROJECTTYPE": "Occupancy",
  "STRUCTURETYPE": 20,
  "STRUCTURETYPENAME": "Commercial",
  "APPLICATIONDATE": "November, 30 2021 00:00:00",
  "ISSUEDATE": "December, 01 2021 00:00:00",
  "DAYSTOISSUE": 1,
  "APPLICATIONDESCRIPTION": "OFFICE- UNITS 300 (PARTIAL PMT)"
}
