{
  "ADDRESS": "3800 WATSON RD",
  "PROJECTTYPE": "Occupancy",
  "STRUCTURETYPE": 20,
  "STRUCTURETYPENAME": "Commercial",
  "APPLICATIONDATE": "January, 12 2022 00:00:00",
  "ISSUEDATE": "January, 14 2022 00:00:00",
  "DAYSTOISSUE": 2,
  "APPLICATIONDESCRIPTION": "DAYCARE ADDITION/32 INF 6 WKS-2 1/2 YRS-6:30A-6P MON-FRI-PMT"
}
{
  "ADDRESS": "4300 HUNT AV",
  "PROJECTTYPE": "Occupancy",
  "STRUCTURETYPE": 20,
  "STRUCTURETYPENAME": "Commercial",
  "APPLICATIONDATE": "January, 13 2022 00:00:00",
  "ISSUEDATE": "January, 13 2022 00:00:00",
  "DAYSTOISSUE": 0,
  "APPLICATIONDESCRIPTION": "HAIR SALON W/RETAIL SALES  (PMT)"
}
{
  "ADDRESS": "3620 TEXAS AV",
  "PROJECTTYPE": "Occupancy",
  "STRUCTURETYPE": 2,
  "STRUCTURETYPENAME": "Multi Family",
  "APPLICATIONDATE": "January, 12 2022 00:00:00",
  "ISSUEDATE": "January, 13 2022 00:00:00",
  "DAYSTOISSUE": 1,
  "APPLICATIONDESCRIPTION": "MULTIFAMILY -12 UNITS (PMT) SEE LIST FOR UNITS & LOADS"
}
{
  "ADDRESS": "2100 LOCUST ST",
  "PROJECTTYPE": "Occupancy",
  "STRUCTURETYPE": 20,
  "STRUCTURETYPENAME": "Commercial",
  "APPLICATIONDATE": "January, 13 2022 00:00:00",
  "ISSUEDATE": "January, 13 2022 00:00:00",
  "DAYSTOISSUE": 0,
  "APPLICATIONDESCRIPTION": "EVENT SPACE-2FL NORTH (STEPHEN F. HALE ROOM)  PMT"
}
{
  "ADDRESS": "1503 CUTTER AV",
  "PROJECTTYPE": "Occupancy",
  "STRUCTURETYPE": 1,
  "STRUCTURETYPENAME": "1 or 2 Family",
  "APPLICATIONDATE": "January, 13 2022 00:00:00",
  "ISSUEDATE": "January, 13 2022 00:00:00",
  "DAYSTOISSUE": 0,
  "APPLICATIONDESCRIPTION": "SINGLE FAMILY  (PMT)"
}
{
  "ADDRESS": "4172 FOLSOM AV",
  "PROJECTTYPE": "Occupancy",
  "STRUCTURETYPE": 1,
  "STRUCTURETYPENAME": "1 or 2 Family",
  "APPLICATIONDATE": "June, 02 2021 00:00:00",
  "ISSUEDATE": "January, 12 2022 00:00:00",
  "DAYSTOISSUE": 224,
  "APPLICATIONDESCRIPTION": "SINGLE FAMILY  (PMT)"
}
{
  "ADDRESS": "3700-20 FOREST PARK AV",
  "PROJECTTYPE": "Occupancy",
  "STRUCTURETYPE": 20,
  "STRUCTURETYPENAME": "Commercial",
  "APPLICATIONDATE": "January, 12 2022 00:00:00",
  "ISSUEDATE": "January, 12 2022 00:00:00",
  "DAYSTOISSUE": 0,
  "APPLICATIONDESCRIPTION": "RETAIL SALES(CLOTHING,GIFTS,PAPERGOODS,PKG FOODS) PART PMT"
}
{
  "ADDRESS": "2345 MICHIGAN AV",
  "PROJECTTYPE": "Occupancy",
  "STRUCTURETYPE": 1,
  "STRUCTURETYPENAME": "1 or 2 Family",
  "APPLICATIONDATE": "August, 05 2021 00:00:00",
  "ISSUEDATE": "January, 12 2022 00:00:00",
  "DAYSTOISSUE": 160,
  "APPLICATIONDESCRIPTION": "SINGLE FAMILY  (PMT)"
}
{
  "ADDRESS": "1833 KNOX AV",
  "PROJECTTYPE": "Occupancy",
  "STRUCTURETYPE": 20,
  "STRUCTURETYPENAME": "Commercial",
  "APPLICATIONDATE": "January, 12 2022 00:00:00",
  "ISSUEDATE": "January, 12 2022 00:00:00",
  "DAYSTOISSUE": 0,
  "APPLICATIONDESCRIPTION": "OFFICE SPACE (RM 1-R) PARTIAL PMT"
}
{
  "ADDRESS": "1010 MARKET ST",
  "PROJECTTYPE": "Occupancy",
  "STRUCTURETYPE": 20,
  "STRUCTURETYPENAME": "Commercial",
  "APPLICATIONDATE": "January, 12 2022 00:00:00",
  "ISSUEDATE": "January, 12 2022 00:00:00",
  "DAYSTOISSUE": 0,
  "APPLICATIONDESCRIPTION": "OFFICE SPACE - STE 1340   (PMT)"
}
{
  "ADDRESS": "900-14 OLIVE ST",
  "PROJECTTYPE": "Occupancy",
  "STRUCTURETYPE": 20,
  "STRUCTURETYPENAME": "Commercial",
  "APPLICATIONDATE": "January, 11 2022 00:00:00",
  "ISSUEDATE": "January, 11 2022 00:00:00",
  "DAYSTOISSUE": 0,
  "APPLICATIONDESCRIPTION": "OFFICE SPACE - STE 600   (PARTIAL PMT)"
}
{
  "ADDRESS": "6622 CHIPPEWA ST",
  "PROJECTTYPE": "Occupancy",
  "STRUCTURETYPE": 20,
  "STRUCTURETYPENAME": "Commercial",
  "APPLICATIONDATE": "January, 04 2022 00:00:00",
  "ISSUEDATE": "January, 07 2022 00:00:00",
  "DAYSTOISSUE": 3,
  "APPLICATIONDESCRIPTION": "COFFEE SHOP  (PMT)"
}
{
  "ADDRESS": "4102 HUMPHREY ST",
  "PROJECTTYPE": "Occupancy",
  "STRUCTURETYPE": 1,
  "STRUCTURETYPENAME": "1 or 2 Family",
  "APPLICATIONDATE": "January, 07 2022 00:00:00",
  "ISSUEDATE": "January, 07 2022 00:00:00",
  "DAYSTOISSUE": 0,
  "APPLICATIONDESCRIPTION": "INTERIOR ALTERATIONS PER PLANS"
}
{
  "ADDRESS": "3700-20 FOREST PARK AV",
  "PROJECTTYPE": "Occupancy",
  "STRUCTURETYPE": 20,
  "STRUCTURETYPENAME": "Commercial",
  "APPLICATIONDATE": "January, 06 2022 00:00:00",
  "ISSUEDATE": "January, 07 2022 00:00:00",
  "DAYSTOISSUE": 1,
  "APPLICATIONDESCRIPTION": "RETAIL SALES OF CLOTHING - STE 129  ( PMT )"
}
{
  "ADDRESS": "6015 FYLER AV",
  "PROJECTTYPE": "Occupancy",
  "STRUCTURETYPE": 1,
  "STRUCTURETYPENAME": "1 or 2 Family",
  "APPLICATIONDATE": "January, 04 2022 00:00:00",
  "ISSUEDATE": "January, 05 2022 00:00:00",
  "DAYSTOISSUE": 1,
  "APPLICATIONDESCRIPTION": "SINGLE FAMILY  (PMT)"
}
{
  "ADDRESS": "2918 LEMP AV",
  "PROJECTTYPE": "Occupancy",
  "STRUCTURETYPE": 1,
  "STRUCTURETYPENAME": "1 or 2 Family",
  "APPLICATIONDATE": "January, 05 2022 00:00:00",
  "ISSUEDATE": "January, 05 2022 00:00:00",
  "DAYSTOISSUE": 0,
  "APPLICATIONDESCRIPTION": "SINGLE FAMILY  (PMT)"
}
{
  "ADDRESS": "1009 ALLEN AV",
  "PROJECTTYPE": "Occupancy",
  "STRUCTURETYPE": 1,
  "STRUCTURETYPENAME": "1 or 2 Family",
  "APPLICATIONDATE": "January, 04 2022 00:00:00",
  "ISSUEDATE": "January, 05 2022 00:00:00",
  "DAYSTOISSUE": 1,
  "APPLICATIONDESCRIPTION": "SINGLE FAMILY  (PMT)"
}
{
  "ADDRESS": "3170-2 OREGON AV",
  "PROJECTTYPE": "Occupancy",
  "STRUCTURETYPE": 2,
  "STRUCTURETYPENAME": "Multi Family",
  "APPLICATIONDATE": "January, 04 2022 00:00:00",
  "ISSUEDATE": "January, 04 2022 00:00:00",
  "DAYSTOISSUE": 0,
  "APPLICATIONDESCRIPTION": "3170 OREGON 1FL, 2FL  (PARTIAL PMT)"
}
{
  "ADDRESS": "5655 PERSHING AV",
  "PROJECTTYPE": "Occupancy",
  "STRUCTURETYPE": 20,
  "STRUCTURETYPENAME": "Commercial",
  "APPLICATIONDATE": "January, 12 2022 00:00:00",
  "ISSUEDATE": "December, 30 2021 00:00:00",
  "DAYSTOISSUE": -13,
  "APPLICATIONDESCRIPTION": "MULTI FAMILY 15 UNITS 618-632  (PARTIAL PMT)"
}
{
  "ADDRESS": "4209 FOLSOM AV",
  "PROJECTTYPE": "Occupancy",
  "STRUCTURETYPE": 10,
  "STRUCTURETYPENAME": "School",
  "APPLICATIONDATE": "January, 04 2022 00:00:00",
  "ISSUEDATE": "December, 30 2021 00:00:00",
  "DAYSTOISSUE": -5,
  "APPLICATIONDESCRIPTION": "SCHOOL - GRADES 1-8 (ENTIRE SCHOOL)  PMT"
}
{
  "ADDRESS": "2001-5 OLIVE ST",
  "PROJECTTYPE": "Occupancy",
  "STRUCTURETYPE": 20,
  "STRUCTURETYPENAME": "Commercial",
  "APPLICATIONDATE": "January, 04 2022 00:00:00",
  "ISSUEDATE": "December, 30 2021 00:00:00",
  "DAYSTOISSUE": -5,
  "APPLICATIONDESCRIPTION": "MEDICAL MARIJUANA DISPENSARY  (PMT)"
}
{
  "ADDRESS": "7135-311 CANTERBURY AV",
  "PROJECTTYPE": "Occupancy",
  "STRUCTURETYPE": 20,
  "STRUCTURETYPENAME": "Commercial",
  "APPLICATIONDATE": "January, 05 2022 00:00:00",
  "ISSUEDATE": "December, 29 2021 00:00:00",
  "DAYSTOISSUE": -7,
  "APPLICATIONDESCRIPTION": "MULTIFAM 20 UNITS #101-108,201-212  (PARTIAL PMT)"
}
{
  "ADDRESS": "2113 ROBERT RUGGERI PL",
  "PROJECTTYPE": "Occupancy",
  "STRUCTURETYPE": 1,
  "STRUCTURETYPENAME": "1 or 2 Family",
  "APPLICATIONDATE": "January, 04 2022 00:00:00",
  "ISSUEDATE": "December, 29 2021 00:00:00",
  "DAYSTOISSUE": -6,
  "APPLICATIONDESCRIPTION": "SINGLE FAMILY  (PMT)"
}
{
  "ADDRESS": "2109 ROBERT RUGGERI PL",
  "PROJECTTYPE": "Occupancy",
  "STRUCTURETYPE": 1,
  "STRUCTURETYPENAME": "1 or 2 Family",
  "APPLICATIONDATE": "December, 29 2021 00:00:00",
  "ISSUEDATE": "December, 29 2021 00:00:00",
  "DAYSTOISSUE": 0,
  "APPLICATIONDESCRIPTION": "SINGLE FAMILY PMT"
}
{
  "ADDRESS": "1352 CENTRAL AV",
  "PROJECTTYPE": "Occupancy",
  "STRUCTURETYPE": 1,
  "STRUCTURETYPENAME": "1 or 2 Family",
  "APPLICATIONDATE": "December, 29 2021 00:00:00",
  "ISSUEDATE": "December, 29 2021 00:00:00",
  "DAYSTOISSUE": 0,
  "APPLICATIONDESCRIPTION": "SINGLE FAMILY PMT"
}
{
  "ADDRESS": "4565-9 MCREE AV",
  "PROJECTTYPE": "Occupancy",
  "STRUCTURETYPE": 20,
  "STRUCTURETYPENAME": "Commercial",
  "APPLICATIONDATE": "January, 03 2022 00:00:00",
  "ISSUEDATE": "December, 28 2021 00:00:00",
  "DAYSTOISSUE": -6,
  "APPLICATIONDESCRIPTION": "OFFICE SPACE - SUITES 1FL-176, 2FL-115, MEZZANINE (PMT)"
}
{
  "ADDRESS": "4565-9 MCREE AV",
  "PROJECTTYPE": "Occupancy",
  "STRUCTURETYPE": 20,
  "STRUCTURETYPENAME": "Commercial",
  "APPLICATIONDATE": "January, 03 2022 00:00:00",
  "ISSUEDATE": "December, 28 2021 00:00:00",
  "DAYSTOISSUE": -6,
  "APPLICATIONDESCRIPTION": "OFFICE SPACE - SUITES 1FL-302 & 2FL-128  (PARTIAL PMT)"
}
{
  "ADDRESS": "2654-60 LOCUST ST",
  "PROJECTTYPE": "Occupancy",
  "STRUCTURETYPE": 2,
  "STRUCTURETYPENAME": "Multi Family",
  "APPLICATIONDATE": "January, 03 2022 00:00:00",
  "ISSUEDATE": "December, 28 2021 00:00:00",
  "DAYSTOISSUE": -6,
  "APPLICATIONDESCRIPTION": "MULTIFAM 9 UNITS-102,103,106,108,109,110,111,112,202(PT PMT)"
}
{
  "ADDRESS": "1229-31 ALLEN MARKET LA",
  "PROJECTTYPE": "Occupancy",
  "STRUCTURETYPE": 1,
  "STRUCTURETYPENAME": "1 or 2 Family",
  "APPLICATIONDATE": "December, 28 2021 00:00:00",
  "ISSUEDATE": "December, 28 2021 00:00:00",
  "DAYSTOISSUE": 0,
  "APPLICATIONDESCRIPTION": "TWO FAMILY (1229 ALLEN MARKET LANE PMT)"
}
{
  "ADDRESS": "1229-31 ALLEN MARKET LA",
  "PROJECTTYPE": "Occupancy",
  "STRUCTURETYPE": 1,
  "STRUCTURETYPENAME": "1 or 2 Family",
  "APPLICATIONDATE": "December, 28 2021 00:00:00",
  "ISSUEDATE": "December, 28 2021 00:00:00",
  "DAYSTOISSUE": 0,
  "APPLICATIONDESCRIPTION": "SINGLE FAMILY PMT"
}
{
  "ADDRESS": "3700-20 FOREST PARK AV",
  "PROJECTTYPE": "Occupancy",
  "STRUCTURETYPE": 20,
  "STRUCTURETYPENAME": "Commercial",
  "APPLICATIONDATE": "January, 07 2022 00:00:00",
  "ISSUEDATE": "December, 27 2021 00:00:00",
  "DAYSTOISSUE": -11,
  "APPLICATIONDESCRIPTION": "FULL DRINK RESTAURANT-STALL 13 (NO OUTSIDE SEATING)  PMT"
}
{
  "ADDRESS": "2929-3101 CHOUTEAU AV",
  "PROJECTTYPE": "Occupancy",
  "STRUCTURETYPE": 20,
  "STRUCTURETYPENAME": "Commercial",
  "APPLICATIONDATE": "January, 12 2022 00:00:00",
  "ISSUEDATE": "December, 27 2021 00:00:00",
  "DAYSTOISSUE": -16,
  "APPLICATIONDESCRIPTION": "2FL MEZZANINE OFFICE SPACE - WEST SIDE OF BLDG  (PMT)"
}
{
  "ADDRESS": "700-10 N TUCKER BLVD",
  "PROJECTTYPE": "Occupancy",
  "STRUCTURETYPE": 20,
  "STRUCTURETYPENAME": "Commercial",
  "APPLICATIONDATE": "December, 23 2021 00:00:00",
  "ISSUEDATE": "December, 23 2021 00:00:00",
  "DAYSTOISSUE": 0,
  "APPLICATIONDESCRIPTION": "OFFICE SPACE- UNIT 110 (PARTIAL PMT)"
}
{
  "ADDRESS": "5500 OAKLAND AV",
  "PROJECTTYPE": "Occupancy",
  "STRUCTURETYPE": 10,
  "STRUCTURETYPENAME": "School",
  "APPLICATIONDATE": "December, 23 2021 00:00:00",
  "ISSUEDATE": "December, 23 2021 00:00:00",
  "DAYSTOISSUE": 0,
  "APPLICATIONDESCRIPTION": "NURSING SCHOOL - PMT"
}
{
  "ADDRESS": "3819 S GRAND BLVD",
  "PROJECTTYPE": "Occupancy",
  "STRUCTURETYPE": 20,
  "STRUCTURETYPENAME": "Commercial",
  "APPLICATIONDATE": "December, 23 2021 00:00:00",
  "ISSUEDATE": "December, 23 2021 00:00:00",
  "DAYSTOISSUE": 0,
  "APPLICATIONDESCRIPTION": "REAL ESTATE OFFICE  (PMT)"
}
{
  "ADDRESS": "1372-92 GRANVILLE PL",
  "PROJECTTYPE": "Occupancy",
  "STRUCTURETYPE": 1,
  "STRUCTURETYPENAME": "1 or 2 Family",
  "APPLICATIONDATE": "January, 05 2022 00:00:00",
  "ISSUEDATE": "December, 23 2021 00:00:00",
  "DAYSTOISSUE": -13,
  "APPLICATIONDESCRIPTION": "1 UNIT (PMT)"
}
{
  "ADDRESS": "1221 LOCUST ST",
  "PROJECTTYPE": "Occupancy",
  "STRUCTURETYPE": 3,
  "STRUCTURETYPENAME": "Hotel",
  "APPLICATIONDATE": "December, 23 2021 00:00:00",
  "ISSUEDATE": "December, 23 2021 00:00:00",
  "DAYSTOISSUE": 0,
  "APPLICATIONDESCRIPTION": "HOTEL-1ST CHECK IN-12TH FLRS & BSMT(LAUNDRY/BRKRM) PMT"
}
{
  "ADDRESS": "1451 CUTTER AV",
  "PROJECTTYPE": "Occupancy",
  "STRUCTURETYPE": 1,
  "STRUCTURETYPENAME": "1 or 2 Family",
  "APPLICATIONDATE": "January, 04 2022 00:00:00",
  "ISSUEDATE": "December, 22 2021 00:00:00",
  "DAYSTOISSUE": -13,
  "APPLICATIONDESCRIPTION": "SINGLE FAMILY  (PMT)"
}
{
  "ADDRESS": "2724-6 S JEFFERSON AV",
  "PROJECTTYPE": "Occupancy",
  "STRUCTURETYPE": 1,
  "STRUCTURETYPENAME": "1 or 2 Family",
  "APPLICATIONDATE": "December, 21 2021 00:00:00",
  "ISSUEDATE": "December, 21 2021 00:00:00",
  "DAYSTOISSUE": 0,
  "APPLICATIONDESCRIPTION": "SINGLE FAMILY   (PMT)"
}
{
  "ADDRESS": "1139 OLIVE ST",
  "PROJECTTYPE": "Occupancy",
  "STRUCTURETYPE": 20,
  "STRUCTURETYPENAME": "Commercial",
  "APPLICATIONDATE": "January, 03 2022 00:00:00",
  "ISSUEDATE": "December, 21 2021 00:00:00",
  "DAYSTOISSUE": -13,
  "APPLICATIONDESCRIPTION": "MULTI FAMILY 5FL-11 UNITS/LEASING OFFC/LOUNGE (PMT)"
}
{
  "ADDRESS": "2760 S 1ST ST",
  "PROJECTTYPE": "Occupancy",
  "STRUCTURETYPE": 20,
  "STRUCTURETYPENAME": "Commercial",
  "APPLICATIONDATE": "January, 05 2022 00:00:00",
  "ISSUEDATE": "December, 20 2021 00:00:00",
  "DAYSTOISSUE": -16,
  "APPLICATIONDESCRIPTION": "WAREHOUSE (INSIDE STORAGE OF ALUMINUM CANS)   (PMT)"
}
