{
  "ADDRESS": "500 N BROADWAY",
  "PROJECTTYPE": "Occupancy",
  "STRUCTURETYPE": 20,
  "STRUCTURETYPENAME": "Commercial",
  "APPLICATIONDATE": "May, 18 2022 00:00:00",
  "ISSUEDATE": "May, 18 2022 00:00:00",
  "DAYSTOISSUE": 0,
  "APPLICATIONDESCRIPTION": "OFFICE SPACE-STE 1650  (PMT)"
}
{
  "ADDRESS": "4545 LACLEDE AV",
  "PROJECTTYPE": "Occupancy",
  "STRUCTURETYPE": 2,
  "STRUCTURETYPENAME": "Multi Family",
  "APPLICATIONDATE": "May, 18 2022 00:00:00",
  "ISSUEDATE": "May, 18 2022 00:00:00",
  "DAYSTOISSUE": 0,
  "APPLICATIONDESCRIPTION": "MULTIFAM 41 UNITS (5FL SEE LIST FOR LOADS/UNITS)PARTIAL PMT"
}
{
  "ADDRESS": "1424 TALMAGE AV",
  "PROJECTTYPE": "Occupancy",
  "STRUCTURETYPE": 20,
  "STRUCTURETYPENAME": "Commercial",
  "APPLICATIONDATE": "May, 18 2022 00:00:00",
  "ISSUEDATE": "May, 18 2022 00:00:00",
  "DAYSTOISSUE": 0,
  "APPLICATIONDESCRIPTION": "MANUFACTURING OF FURNITURE - PMT"
}
{
  "ADDRESS": "4151-3 BOTANICAL AV",
  "PROJECTTYPE": "Occupancy",
  "STRUCTURETYPE": 2,
  "STRUCTURETYPENAME": "Multi Family",
  "APPLICATIONDATE": "May, 17 2022 00:00:00",
  "ISSUEDATE": "May, 17 2022 00:00:00",
  "DAYSTOISSUE": 0,
  "APPLICATIONDESCRIPTION": "TWO UNITS 1FL, 2FL  (PMT)"
}
{
  "ADDRESS": "2819 VICTOR ST",
  "PROJECTTYPE": "Occupancy",
  "STRUCTURETYPE": 1,
  "STRUCTURETYPENAME": "1 or 2 Family",
  "APPLICATIONDATE": "May, 16 2022 00:00:00",
  "ISSUEDATE": "May, 16 2022 00:00:00",
  "DAYSTOISSUE": 0,
  "APPLICATIONDESCRIPTION": "SINGLE FAMILY  (PMT)"
}
{
  "ADDRESS": "5722 NEOSHO ST",
  "PROJECTTYPE": "Occupancy",
  "STRUCTURETYPE": 1,
  "STRUCTURETYPENAME": "1 or 2 Family",
  "APPLICATIONDATE": "May, 13 2022 00:00:00",
  "ISSUEDATE": "May, 13 2022 00:00:00",
  "DAYSTOISSUE": 0,
  "APPLICATIONDESCRIPTION": "SINGLE FAMILY- PMT"
}
{
  "ADDRESS": "5655 PERSHING AV",
  "PROJECTTYPE": "Occupancy",
  "STRUCTURETYPE": 15,
  "STRUCTURETYPENAME": "Parking Station",
  "APPLICATIONDATE": "May, 13 2022 00:00:00",
  "ISSUEDATE": "May, 13 2022 00:00:00",
  "DAYSTOISSUE": 0,
  "APPLICATIONDESCRIPTION": "MULTI FAMILY-LOWER LEVEL GARAGE & 1FL GARAGE (PARTIAL PMT)"
}
{
  "ADDRESS": "4059-61 SHAW AV",
  "PROJECTTYPE": "Occupancy",
  "STRUCTURETYPE": 2,
  "STRUCTURETYPENAME": "Multi Family",
  "APPLICATIONDATE": "May, 13 2022 00:00:00",
  "ISSUEDATE": "May, 13 2022 00:00:00",
  "DAYSTOISSUE": 0,
  "APPLICATIONDESCRIPTION": "TWO UNITS- 4059 & 4061 (PMT)"
}
{
  "ADDRESS": "6216 DELOR ST",
  "PROJECTTYPE": "Occupancy",
  "STRUCTURETYPE": 1,
  "STRUCTURETYPENAME": "1 or 2 Family",
  "APPLICATIONDATE": "May, 12 2022 00:00:00",
  "ISSUEDATE": "May, 12 2022 00:00:00",
  "DAYSTOISSUE": 0,
  "APPLICATIONDESCRIPTION": "SINGLE FAMILY  (PMT)"
}
{
  "ADDRESS": "5655 PERSHING AV",
  "PROJECTTYPE": "Occupancy",
  "STRUCTURETYPE": 20,
  "STRUCTURETYPENAME": "Commercial",
  "APPLICATIONDATE": "May, 12 2022 00:00:00",
  "ISSUEDATE": "May, 12 2022 00:00:00",
  "DAYSTOISSUE": 0,
  "APPLICATIONDESCRIPTION": "LEVEL 6 SKYLOUNGE  (PARTIAL PMT)"
}
{
  "ADDRESS": "3700-20 FOREST PARK AV",
  "PROJECTTYPE": "Occupancy",
  "STRUCTURETYPE": 20,
  "STRUCTURETYPENAME": "Commercial",
  "APPLICATIONDATE": "May, 12 2022 00:00:00",
  "ISSUEDATE": "May, 12 2022 00:00:00",
  "DAYSTOISSUE": 0,
  "APPLICATIONDESCRIPTION": "RESTAURANT-STALL 17  (NO ALCOHOL,NO OUTSIDE SEATING)  PMT"
}
{
  "ADDRESS": "3420-8 S JEFFERSON AV",
  "PROJECTTYPE": "Occupancy",
  "STRUCTURETYPE": 20,
  "STRUCTURETYPENAME": "Commercial",
  "APPLICATIONDATE": "May, 12 2022 00:00:00",
  "ISSUEDATE": "May, 12 2022 00:00:00",
  "DAYSTOISSUE": 0,
  "APPLICATIONDESCRIPTION": "CARRYOUT RESTAURANT (NO LIQUOR, NO OUTSIDE SEATING) PMT"
}
{
  "ADDRESS": "3201-25 DELMAR BLVD",
  "PROJECTTYPE": "Occupancy",
  "STRUCTURETYPE": 2,
  "STRUCTURETYPENAME": "Multi Family",
  "APPLICATIONDATE": "May, 12 2022 00:00:00",
  "ISSUEDATE": "May, 12 2022 00:00:00",
  "DAYSTOISSUE": 0,
  "APPLICATIONDESCRIPTION": "TWO UNITS B & D  (PMT)"
}
{
  "ADDRESS": "2626-34 HICKORY ST",
  "PROJECTTYPE": "Occupancy",
  "STRUCTURETYPE": 20,
  "STRUCTURETYPENAME": "Commercial",
  "APPLICATIONDATE": "May, 10 2022 00:00:00",
  "ISSUEDATE": "May, 12 2022 00:00:00",
  "DAYSTOISSUE": 2,
  "APPLICATIONDESCRIPTION": "SINGLE UNIT (PMT)"
}
{
  "ADDRESS": "3333 VIRGINIA AV",
  "PROJECTTYPE": "Occupancy",
  "STRUCTURETYPE": 1,
  "STRUCTURETYPENAME": "1 or 2 Family",
  "APPLICATIONDATE": "May, 06 2022 00:00:00",
  "ISSUEDATE": "May, 06 2022 00:00:00",
  "DAYSTOISSUE": 0,
  "APPLICATIONDESCRIPTION": "SINGLE FAMILY  (PMT)"
}
{
  "ADDRESS": "5613 WILSON AV",
  "PROJECTTYPE": "Occupancy",
  "STRUCTURETYPE": 1,
  "STRUCTURETYPENAME": "1 or 2 Family",
  "APPLICATIONDATE": "May, 05 2022 00:00:00",
  "ISSUEDATE": "May, 05 2022 00:00:00",
  "DAYSTOISSUE": 0,
  "APPLICATIONDESCRIPTION": "SINGLE FAMILY  (PMT)"
}
{
  "ADDRESS": "5501-35 DELMAR BLVD",
  "PROJECTTYPE": "Occupancy",
  "STRUCTURETYPE": 20,
  "STRUCTURETYPENAME": "Commercial",
  "APPLICATIONDATE": "May, 05 2022 00:00:00",
  "ISSUEDATE": "May, 05 2022 00:00:00",
  "DAYSTOISSUE": 0,
  "APPLICATIONDESCRIPTION": "OFFICE SPACE #B200  (PMT)"
}
{
  "ADDRESS": "501-25 N BROADWAY",
  "PROJECTTYPE": "Occupancy",
  "STRUCTURETYPE": 20,
  "STRUCTURETYPENAME": "Commercial",
  "APPLICATIONDATE": "May, 05 2022 00:00:00",
  "ISSUEDATE": "May, 05 2022 00:00:00",
  "DAYSTOISSUE": 0,
  "APPLICATIONDESCRIPTION": "OFFICE SPACE - 6FL  (PMT)"
}
{
  "ADDRESS": "4650-60 CHIPPEWA ST",
  "PROJECTTYPE": "Occupancy",
  "STRUCTURETYPE": 20,
  "STRUCTURETYPENAME": "Commercial",
  "APPLICATIONDATE": "May, 05 2022 00:00:00",
  "ISSUEDATE": "May, 05 2022 00:00:00",
  "DAYSTOISSUE": 0,
  "APPLICATIONDESCRIPTION": "CLINIC-OFFICE- STE B (PART. PMT)"
}
{
  "ADDRESS": "3953 EILER ST",
  "PROJECTTYPE": "Occupancy",
  "STRUCTURETYPE": 1,
  "STRUCTURETYPENAME": "1 or 2 Family",
  "APPLICATIONDATE": "May, 05 2022 00:00:00",
  "ISSUEDATE": "May, 05 2022 00:00:00",
  "DAYSTOISSUE": 0,
  "APPLICATIONDESCRIPTION": "SINGLE FAMILY   (PMT)"
}
{
  "ADDRESS": "3822 CASTLEMAN AV",
  "PROJECTTYPE": "Occupancy",
  "STRUCTURETYPE": 1,
  "STRUCTURETYPENAME": "1 or 2 Family",
  "APPLICATIONDATE": "May, 05 2022 00:00:00",
  "ISSUEDATE": "May, 05 2022 00:00:00",
  "DAYSTOISSUE": 0,
  "APPLICATIONDESCRIPTION": "SINGLE FAMILY  (PMT)"
}
{
  "ADDRESS": "2737 UTAH ST",
  "PROJECTTYPE": "Occupancy",
  "STRUCTURETYPE": 1,
  "STRUCTURETYPENAME": "1 or 2 Family",
  "APPLICATIONDATE": "May, 05 2022 00:00:00",
  "ISSUEDATE": "May, 05 2022 00:00:00",
  "DAYSTOISSUE": 0,
  "APPLICATIONDESCRIPTION": "SINGLE FAMILY  (PMT)"
}
{
  "ADDRESS": "801-35 CHOUTEAU AV",
  "PROJECTTYPE": "Occupancy",
  "STRUCTURETYPE": 20,
  "STRUCTURETYPENAME": "Commercial",
  "APPLICATIONDATE": "May, 04 2022 00:00:00",
  "ISSUEDATE": "May, 04 2022 00:00:00",
  "DAYSTOISSUE": 0,
  "APPLICATIONDESCRIPTION": "OFFICE SPACE  (PARTIAL PMT)"
}
{
  "ADDRESS": "1313 S BOYLE AV",
  "PROJECTTYPE": "Occupancy",
  "STRUCTURETYPE": 1,
  "STRUCTURETYPENAME": "1 or 2 Family",
  "APPLICATIONDATE": "May, 04 2022 00:00:00",
  "ISSUEDATE": "May, 04 2022 00:00:00",
  "DAYSTOISSUE": 0,
  "APPLICATIONDESCRIPTION": "SINGLE FAMILY  (PMT)"
}
{
  "ADDRESS": "7135-311 CANTERBURY AV",
  "PROJECTTYPE": "Occupancy",
  "STRUCTURETYPE": 20,
  "STRUCTURETYPENAME": "Commercial",
  "APPLICATIONDATE": "May, 03 2022 00:00:00",
  "ISSUEDATE": "May, 03 2022 00:00:00",
  "DAYSTOISSUE": 0,
  "APPLICATIONDESCRIPTION": "MULTIFAM 9 UNITS 301-309  (PARTIAL PMT)"
}
{
  "ADDRESS": "5760 CHIPPEWA ST",
  "PROJECTTYPE": "Occupancy",
  "STRUCTURETYPE": 20,
  "STRUCTURETYPENAME": "Commercial",
  "APPLICATIONDATE": "May, 03 2022 00:00:00",
  "ISSUEDATE": "May, 03 2022 00:00:00",
  "DAYSTOISSUE": 0,
  "APPLICATIONDESCRIPTION": "RETAIL SALES OF LIQUOR,BEE,WINE,PKG FOOD,ACCESSORIES  (PMT)"
}
{
  "ADDRESS": "3418 VISTA AV",
  "PROJECTTYPE": "Occupancy",
  "STRUCTURETYPE": 1,
  "STRUCTURETYPENAME": "1 or 2 Family",
  "APPLICATIONDATE": "February, 11 2022 00:00:00",
  "ISSUEDATE": "May, 03 2022 00:00:00",
  "DAYSTOISSUE": 81,
  "APPLICATIONDESCRIPTION": "SINGLE FAMILY  (PMT)"
}
{
  "ADDRESS": "7327 YATES ST",
  "PROJECTTYPE": "Occupancy",
  "STRUCTURETYPE": 1,
  "STRUCTURETYPENAME": "1 or 2 Family",
  "APPLICATIONDATE": "May, 02 2022 00:00:00",
  "ISSUEDATE": "May, 02 2022 00:00:00",
  "DAYSTOISSUE": 0,
  "APPLICATIONDESCRIPTION": "SINGLE FAMILY   (PMT)"
}
{
  "ADDRESS": "4109 QUINCY ST",
  "PROJECTTYPE": "Occupancy",
  "STRUCTURETYPE": 1,
  "STRUCTURETYPENAME": "1 or 2 Family",
  "APPLICATIONDATE": "May, 02 2022 00:00:00",
  "ISSUEDATE": "May, 02 2022 00:00:00",
  "DAYSTOISSUE": 0,
  "APPLICATIONDESCRIPTION": "SINGLE FAMILY  (PMT)"
}
{
  "ADDRESS": "4172 FOLSOM AV",
  "PROJECTTYPE": "Occupancy",
  "STRUCTURETYPE": 1,
  "STRUCTURETYPENAME": "1 or 2 Family",
  "APPLICATIONDATE": "April, 29 2022 00:00:00",
  "ISSUEDATE": "April, 29 2022 00:00:00",
  "DAYSTOISSUE": 0,
  "APPLICATIONDESCRIPTION": "SINGLE FAMILY  (PMT)"
}
{
  "ADDRESS": "3538 CALIFORNIA AV",
  "PROJECTTYPE": "Occupancy",
  "STRUCTURETYPE": 1,
  "STRUCTURETYPENAME": "1 or 2 Family",
  "APPLICATIONDATE": "April, 29 2022 00:00:00",
  "ISSUEDATE": "April, 29 2022 00:00:00",
  "DAYSTOISSUE": 0,
  "APPLICATIONDESCRIPTION": "SINGLE FAMILY  (PMT)"
}
{
  "ADDRESS": "1450 N 18TH ST",
  "PROJECTTYPE": "Occupancy",
  "STRUCTURETYPE": 20,
  "STRUCTURETYPENAME": "Commercial",
  "APPLICATIONDATE": "May, 17 2022 00:00:00",
  "ISSUEDATE": "April, 29 2022 00:00:00",
  "DAYSTOISSUE": -18,
  "APPLICATIONDESCRIPTION": "MULTIFAM 6UNITS 1601,1603,1605,1607,1609,1611-BLDG L(PT PMT)"
}
{
  "ADDRESS": "1450 N 18TH ST",
  "PROJECTTYPE": "Occupancy",
  "STRUCTURETYPE": 20,
  "STRUCTURETYPENAME": "Commercial",
  "APPLICATIONDATE": "May, 12 2022 00:00:00",
  "ISSUEDATE": "April, 29 2022 00:00:00",
  "DAYSTOISSUE": -13,
  "APPLICATIONDESCRIPTION": "MULTIFM 6UNITS 1701,1703,1705,1707,1709,1711-BLDG O(PART PMT"
}
{
  "ADDRESS": "1450 N 18TH ST",
  "PROJECTTYPE": "Occupancy",
  "STRUCTURETYPE": 20,
  "STRUCTURETYPENAME": "Commercial",
  "APPLICATIONDATE": "May, 12 2022 00:00:00",
  "ISSUEDATE": "April, 29 2022 00:00:00",
  "DAYSTOISSUE": -13,
  "APPLICATIONDESCRIPTION": "MULTI FAMILY 4 UNITS 1433,1435,1437,1439-BLDG K (PARTIAL PMT"
}
{
  "ADDRESS": "1450 N 18TH ST",
  "PROJECTTYPE": "Occupancy",
  "STRUCTURETYPE": 20,
  "STRUCTURETYPENAME": "Commercial",
  "APPLICATIONDATE": "May, 12 2022 00:00:00",
  "ISSUEDATE": "April, 29 2022 00:00:00",
  "DAYSTOISSUE": -13,
  "APPLICATIONDESCRIPTION": "MULFAM 6UNITS 1443,1445,1447,1449,1451,1453-BLDG J(PART PMT)"
}
{
  "ADDRESS": "1450 N 18TH ST",
  "PROJECTTYPE": "Occupancy",
  "STRUCTURETYPE": 20,
  "STRUCTURETYPENAME": "Commercial",
  "APPLICATIONDATE": "May, 12 2022 00:00:00",
  "ISSUEDATE": "April, 29 2022 00:00:00",
  "DAYSTOISSUE": -13,
  "APPLICATIONDESCRIPTION": "MULTIFAM 6UNITS 1606,1608,1610,1612,1614,1616-BLDG I(PT PMT"
}
{
  "ADDRESS": "1450 N 18TH ST",
  "PROJECTTYPE": "Occupancy",
  "STRUCTURETYPE": 20,
  "STRUCTURETYPENAME": "Commercial",
  "APPLICATIONDATE": "May, 12 2022 00:00:00",
  "ISSUEDATE": "April, 29 2022 00:00:00",
  "DAYSTOISSUE": -13,
  "APPLICATIONDESCRIPTION": "MULTI FAM 4 UNITS 1620,1622,1624,1626-BLDG H (PARTIAL PMT)"
}
{
  "ADDRESS": "1450 N 18TH ST",
  "PROJECTTYPE": "Occupancy",
  "STRUCTURETYPE": 20,
  "STRUCTURETYPENAME": "Commercial",
  "APPLICATIONDATE": "April, 29 2022 00:00:00",
  "ISSUEDATE": "April, 29 2022 00:00:00",
  "DAYSTOISSUE": 0,
  "APPLICATIONDESCRIPTION": "MULTI FAM 4 UNITS 1630,1632,1634,1636-BLDG G (PARTIAL PMT)"
}
{
  "ADDRESS": "1450 N 18TH ST",
  "PROJECTTYPE": "Occupancy",
  "STRUCTURETYPE": 20,
  "STRUCTURETYPENAME": "Commercial",
  "APPLICATIONDATE": "April, 29 2022 00:00:00",
  "ISSUEDATE": "April, 29 2022 00:00:00",
  "DAYSTOISSUE": 0,
  "APPLICATIONDESCRIPTION": "MULTIFAM  4 UNITS 1640,1700,1702,1704-BLDG F (PARTIAL PMT)"
}
{
  "ADDRESS": "100 N BROADWAY",
  "PROJECTTYPE": "Occupancy",
  "STRUCTURETYPE": 20,
  "STRUCTURETYPENAME": "Commercial",
  "APPLICATIONDATE": "April, 29 2022 00:00:00",
  "ISSUEDATE": "April, 29 2022 00:00:00",
  "DAYSTOISSUE": 0,
  "APPLICATIONDESCRIPTION": "OFFICE SPACE-FLOORS 1,2,11  (PMT)"
}
{
  "ADDRESS": "3323-9 PARK AV",
  "PROJECTTYPE": "Occupancy",
  "STRUCTURETYPE": 2,
  "STRUCTURETYPENAME": "Multi Family",
  "APPLICATIONDATE": "April, 28 2022 00:00:00",
  "ISSUEDATE": "April, 28 2022 00:00:00",
  "DAYSTOISSUE": 0,
  "APPLICATIONDESCRIPTION": "TWO UNITS-3323 & 3325 -PMT"
}
{
  "ADDRESS": "2704-8 MCNAIR AV",
  "PROJECTTYPE": "Occupancy",
  "STRUCTURETYPE": 1,
  "STRUCTURETYPENAME": "1 or 2 Family",
  "APPLICATIONDATE": "April, 27 2022 00:00:00",
  "ISSUEDATE": "April, 27 2022 00:00:00",
  "DAYSTOISSUE": 0,
  "APPLICATIONDESCRIPTION": "SINGLE FAMILY-PMT"
}
{
  "ADDRESS": "4366 HUNT AV",
  "PROJECTTYPE": "Occupancy",
  "STRUCTURETYPE": 1,
  "STRUCTURETYPENAME": "1 or 2 Family",
  "APPLICATIONDATE": "February, 28 2022 00:00:00",
  "ISSUEDATE": "April, 26 2022 00:00:00",
  "DAYSTOISSUE": 57,
  "APPLICATIONDESCRIPTION": "SINGLE FAMILY  (PMT)"
}
{
  "ADDRESS": "4109 MCREE AV",
  "PROJECTTYPE": "Occupancy",
  "STRUCTURETYPE": 1,
  "STRUCTURETYPENAME": "1 or 2 Family",
  "APPLICATIONDATE": "April, 26 2022 00:00:00",
  "ISSUEDATE": "April, 26 2022 00:00:00",
  "DAYSTOISSUE": 0,
  "APPLICATIONDESCRIPTION": "SINGLE FAMILY  (PMT)"
}
{
  "ADDRESS": "4906 WEST PINE BLVD",
  "PROJECTTYPE": "Occupancy",
  "STRUCTURETYPE": 20,
  "STRUCTURETYPENAME": "Commercial",
  "APPLICATIONDATE": "April, 22 2022 00:00:00",
  "ISSUEDATE": "April, 22 2022 00:00:00",
  "DAYSTOISSUE": 0,
  "APPLICATIONDESCRIPTION": "SITDOWN/CARRYOUT RESTAURANT(NO OUTSIDE SEAT, NO ALCOHOL)PMT"
}
{
  "ADDRESS": "3458 CHIPPEWA ST",
  "PROJECTTYPE": "Occupancy",
  "STRUCTURETYPE": 1,
  "STRUCTURETYPENAME": "1 or 2 Family",
  "APPLICATIONDATE": "April, 22 2022 00:00:00",
  "ISSUEDATE": "April, 22 2022 00:00:00",
  "DAYSTOISSUE": 0,
  "APPLICATIONDESCRIPTION": "1 UNIT 3458 CHIPPEWA #A  (PMT)"
}
{
  "ADDRESS": "6400-4 GRAVOIS AV",
  "PROJECTTYPE": "Occupancy",
  "STRUCTURETYPE": 20,
  "STRUCTURETYPENAME": "Commercial",
  "APPLICATIONDATE": "April, 21 2022 00:00:00",
  "ISSUEDATE": "April, 21 2022 00:00:00",
  "DAYSTOISSUE": 0,
  "APPLICATIONDESCRIPTION": "CONVENIENCE STORE W/ FULL PKG LIQUOR-PART PMT"
}
{
  "ADDRESS": "5811 CHIPPEWA ST",
  "PROJECTTYPE": "Occupancy",
  "STRUCTURETYPE": 20,
  "STRUCTURETYPENAME": "Commercial",
  "APPLICATIONDATE": "April, 20 2022 00:00:00",
  "ISSUEDATE": "April, 20 2022 00:00:00",
  "DAYSTOISSUE": 0,
  "APPLICATIONDESCRIPTION": "CHIROPRACTIC OFFICE (PMT)"
}
{
  "ADDRESS": "3729 OREGON AV",
  "PROJECTTYPE": "Occupancy",
  "STRUCTURETYPE": 1,
  "STRUCTURETYPENAME": "1 or 2 Family",
  "APPLICATIONDATE": "April, 19 2022 00:00:00",
  "ISSUEDATE": "April, 20 2022 00:00:00",
  "DAYSTOISSUE": 1,
  "APPLICATIONDESCRIPTION": "SINGLE FAMILY  (PMT)"
}
